django_naomi-0.8.dist-info/DESCRIPTION.rst
django_naomi-0.8.dist-info/entry_points.txt
django_naomi-0.8.dist-info/METADATA
django_naomi-0.8.dist-info/metadata.json
django_naomi-0.8.dist-info/RECORD
django_naomi-0.8.dist-info/top_level.txt
django_naomi-0.8.dist-info/WHEEL
naomi/__init__.py
naomi/mail/__init__.py
naomi/mail/backends/__init__.py
naomi/mail/backends/naomi.py
naomi/templates/naomi/message.html
