Metadata-Version: 1.1
Name: django-naomi
Version: 0.8
Summary: Email backend for Django. Preview your email in browser instead of sending it.
Home-page: https://github.com/edwinlunando/django-naomi
Author: Edwin Lunando
Author-email: edwinlunando@gmail.com
License: MIT
Keywords: django email
Platform: UNKNOWN
Classifier: Development Status :: 4 - Beta
Classifier: Intended Audience :: Developers
Classifier: Topic :: Software Development :: Build Tools
Classifier: License :: OSI Approved :: MIT License
Classifier: Programming Language :: Python :: 2
Classifier: Programming Language :: Python :: 2.6
Classifier: Programming Language :: Python :: 2.7
Classifier: Programming Language :: Python :: 3
Classifier: Programming Language :: Python :: 3.2
Classifier: Programming Language :: Python :: 3.3
Classifier: Programming Language :: Python :: 3.4
